Metadata-Version: 2.1
Name: pyhdbsql
Version: 0.0.6
Summary: Python based sql console
Home-page: https://github.com/thhapke/pyhdbsql
Author: Thorsten Hapke
Author-email: thorsten.hapke@sap.com
License: UNKNOWN
Keywords: hana, hdbcli
Platform: UNKNOWN
Classifier: Programming Language :: Python :: 3.6
Classifier: Programming Language :: Python :: 3.7
Classifier: Programming Language :: Python :: 3.8
Classifier: License :: OSI Approved :: MIT License
Classifier: Operating System :: OS Independent
